<?xml version="1.0" encoding="UTF-8"?>
<eventCalendar xmlns="com/tylert/xmlBeans/eventCalendar.xsd">
    <events>
        <day id="-1739790076" bgcolor="#e05ee0" fgcolor="#ffffff">
            <what>Midweek Prayer and Bible Study</what>
            <startDate>2011-9-26</startDate>
            <startHour>19</startHour>
            <startMinute>15</startMinute>
            <startAmPm>PM</startAmPm>
            <endDate>2011-9-26</endDate>
            <endHour>20</endHour>
            <endMinute>15</endMinute>
            <endAmPm>PM</endAmPm>
        </day>
        <day id="654926878" bgcolor="#e05ee0" fgcolor="#ffffff">
            <what>Midweek Prayer and Bible Study</what>
            <startDate>2011-10-2</startDate>
            <startHour>19</startHour>
            <startMinute>15</startMinute>
            <startAmPm>PM</startAmPm>
            <endDate>2011-10-2</endDate>
            <endHour>20</endHour>
            <endMinute>15</endMinute>
            <endAmPm>PM</endAmPm>
        </day>
        <day id="419759942" bgcolor="#e05ee0" fgcolor="#ffffff">
            <what>Sunday Service</what>
            <startDate>2011-9-30</startDate>
            <startHour>10</startHour>
            <startMinute>30</startMinute>
            <startAmPm>AM</startAmPm>
            <endDate>2011-9-30</endDate>
            <endHour>12</endHour>
            <endMinute>30</endMinute>
            <endAmPm>PM</endAmPm>
        </day>
         <day id="419759942" bgcolor="#e05ee0" fgcolor="#ffffff">
            <what>Sunday Service</what>
            <startDate>2011-10-6</startDate>
            <startHour>10</startHour>
            <startMinute>30</startMinute>
            <startAmPm>AM</startAmPm>
            <endDate>2011-10-6</endDate>
            <endHour>12</endHour>
            <endMinute>30</endMinute>
            <endAmPm>PM</endAmPm>
        </day>
         <day id="419759942" bgcolor="#e05ee0" fgcolor="#ffffff">
            <what>Sunday Service</what>
            <startDate>2011-10-13</startDate>
            <startHour>10</startHour>
            <startMinute>30</startMinute>
            <startAmPm>AM</startAmPm>
            <endDate>2011-10-13</endDate>
            <endHour>12</endHour>
            <endMinute>30</endMinute>
            <endAmPm>PM</endAmPm>
        </day>
         <day id="419759942" bgcolor="#e05ee0" fgcolor="#ffffff">
            <what>Sunday Service</what>
            <startDate>2011-10-20</startDate>
            <startHour>10</startHour>
            <startMinute>30</startMinute>
            <startAmPm>AM</startAmPm>
            <endDate>2011-10-20</endDate>
            <endHour>12</endHour>
            <endMinute>30</endMinute>
            <endAmPm>PM</endAmPm>
        </day>
         <day id="419759942" bgcolor="#e05ee0" fgcolor="#ffffff">
            <what>Sunday Service</what>
            <startDate>2011-10-27</startDate>
            <startHour>10</startHour>
            <startMinute>30</startMinute>
            <startAmPm>AM</startAmPm>
            <endDate>2011-10-27</endDate>
            <endHour>12</endHour>
            <endMinute>30</endMinute>
            <endAmPm>PM</endAmPm>
        </day>
        <day id="654926878" bgcolor="#e05ee0" fgcolor="#ffffff">
            <what>Midweek Prayer and Bible Study</what>
            <startDate>2011-10-9</startDate>
            <startHour>19</startHour>
            <startMinute>15</startMinute>
            <startAmPm>PM</startAmPm>
            <endDate>2011-10-9</endDate>
            <endHour>20</endHour>
            <endMinute>15</endMinute>
            <endAmPm>PM</endAmPm>
        </day>
        <day id="654926878" bgcolor="#e05ee0" fgcolor="#ffffff">
            <what>Midweek Prayer and Bible Study</what>
            <startDate>2011-10-16</startDate>
            <startHour>19</startHour>
            <startMinute>15</startMinute>
            <startAmPm>PM</startAmPm>
            <endDate>2011-10-16</endDate>
            <endHour>20</endHour>
            <endMinute>15</endMinute>
            <endAmPm>PM</endAmPm>
        </day>
        <day id="654926878" bgcolor="#e05ee0" fgcolor="#ffffff">
            <what>Midweek Prayer and Bible Study</what>
            <startDate>2011-10-23</startDate>
            <startHour>19</startHour>
            <startMinute>15</startMinute>
            <startAmPm>PM</startAmPm>
            <endDate>2011-10-23</endDate>
            <endHour>20</endHour>
            <endMinute>15</endMinute>
            <endAmPm>PM</endAmPm>
        </day>
        <day id="654926878" bgcolor="#e05ee0" fgcolor="#ffffff">
            <what>Midweek Prayer and Bible Study</what>
            <startDate>2011-10-30</startDate>
            <startHour>19</startHour>
            <startMinute>15</startMinute>
            <startAmPm>PM</startAmPm>
            <endDate>2011-10-30</endDate>
            <endHour>20</endHour>
            <endMinute>15</endMinute>
            <endAmPm>PM</endAmPm>
        </day>
    </events>
</eventCalendar>